{
 "charts": [],
 "content": "[{\"id\":\"hdr1\",\"type\":\"header\",\"data\":{\"text\":\"<span class=\\\"h4\\\"><b>Thermocole Manufacturing</b></span>\",\"col\":12}},{\"id\":\"sc1\",\"type\":\"shortcut\",\"data\":{\"shortcut_name\":\"Thermocole Production Order\",\"col\":4}},{\"id\":\"sc2\",\"type\":\"shortcut\",\"data\":{\"shortcut_name\":\"Thermocole Production Entry\",\"col\":4}},{\"id\":\"sc3\",\"type\":\"shortcut\",\"data\":{\"shortcut_name\":\"Thermocole Quality Inspection\",\"col\":4}}]",
 "creation": "2026-06-25 00:00:00.000000",
 "custom_blocks": [],
 "docstatus": 0,
 "doctype": "Workspace",
 "for_user": "",
 "hide_custom": 0,
 "icon": "package",
 "idx": 0,
 "is_hidden": 0,
 "label": "Thermocole",
 "links": [
  {
   "hidden": 0,
   "is_query_report": 0,
   "label": "Masters",
   "link_count": 0,
   "onboard": 0,
   "type": "Card Break"
  },
  {
   "hidden": 0,
   "is_query_report": 0,
   "label": "Thermocole Mould",
   "link_count": 0,
   "link_to": "Thermocole Mould",
   "link_type": "DocType",
   "onboard": 1,
   "type": "Link"
  },
  {
   "hidden": 0,
   "is_query_report": 0,
   "label": "Thermocole Machine",
   "link_count": 0,
   "link_to": "Thermocole Machine",
   "link_type": "DocType",
   "onboard": 1,
   "type": "Link"
  },
  {
   "hidden": 0,
   "is_query_report": 0,
   "label": "Planning",
   "link_count": 0,
   "onboard": 0,
   "type": "Card Break"
  },
  {
   "hidden": 0,
   "is_query_report": 0,
   "label": "Thermocole Production Order",
   "link_count": 0,
   "link_to": "Thermocole Production Order",
   "link_type": "DocType",
   "onboard": 1,
   "type": "Link"
  },
  {
   "hidden": 0,
   "is_query_report": 0,
   "label": "Shop Floor",
   "link_count": 0,
   "onboard": 0,
   "type": "Card Break"
  },
  {
   "hidden": 0,
   "is_query_report": 0,
   "label": "Thermocole Production Entry",
   "link_count": 0,
   "link_to": "Thermocole Production Entry",
   "link_type": "DocType",
   "onboard": 1,
   "type": "Link"
  },
  {
   "hidden": 0,
   "is_query_report": 0,
   "label": "Thermocole Quality Inspection",
   "link_count": 0,
   "link_to": "Thermocole Quality Inspection",
   "link_type": "DocType",
   "onboard": 1,
   "type": "Link"
  }
 ],
 "modified": "2026-06-25 00:00:00.000000",
 "modified_by": "Administrator",
 "module": "Thermocole",
 "name": "Thermocole",
 "number_cards": [],
 "owner": "Administrator",
 "parent_page": "",
 "public": 1,
 "quick_lists": [],
 "restrict_to_domain": "",
 "roles": [],
 "sequence_id": 21,
 "shortcuts": [
  {
   "color": "Orange",
   "doc_view": "List",
   "label": "Thermocole Production Order",
   "link_to": "Thermocole Production Order",
   "type": "DocType"
  },
  {
   "color": "Green",
   "doc_view": "List",
   "label": "Thermocole Production Entry",
   "link_to": "Thermocole Production Entry",
   "type": "DocType"
  },
  {
   "color": "Blue",
   "doc_view": "List",
   "label": "Thermocole Quality Inspection",
   "link_to": "Thermocole Quality Inspection",
   "type": "DocType"
  }
 ],
 "title": "Thermocole"
}
